Modulos/BintoBcd/AjusteBCD.v
module Ajuste_BCD (
    input [15:0] bcd_in,
    output [15:0] bcd_out,
    output need_adj
);
    wire [3:0] u = bcd_in[3:0];
    wire [3:0] d = bcd_in[7:4];
    wire [3:0] c = bcd_in[11:8];
    wire [3:0] m = bcd_in[15:12];
    wire uu = (u >= 5);
    wire dd = (d >= 5);
    wire cc = (c >= 5);
    wire mm = (m >= 5);
    assign need_adj = (uu | dd | cc | mm);
    wire [3:0] u_next = uu ? (u + 3) : u;
    wire [3:0] d_next = dd ? (d + 3) : d;
    wire [3:0] c_next = cc ? (c + 3) : c;
    wire [3:0] m_next = mm ? (m + 3) : m;
    assign bcd_out = {m_next, c_next, d_next, u_next};
endmodule
module comparador (
    input [4:0] in, input [4:0] COMP, output equal                    
);
    assign equal = (in == COMP);
endmodule
module contador (
    input clk, input rst, input en, output reg [4:0] count    
);
    always @(posedge clk) begin
        if (rst) count <= 0; 
        else if (en) count <= count + 1'b1;  
    end
endmodule

Modulos/BintoBcd/SumadorRestador5_C2.v
module SumadorRestador_C2_5b (
    input sum,
    input restar,
    input [4:0] Aext,
    input [4:0] B,
    output reg [4:0] result
);
    always @(*) begin
        if (sum) begin
            result = Aext + B;
        end
        else if (restar) begin
            result = Aext + (~B) + 1;
        end
        else begin
            result = Aext;
        end
    end
endmodule

Modulos/BintoBcd/RegistroBcd.v
module Registro_Shift_BCD (
    input clk,
    input rst,
    input sumi,
    input eval,
    input [12:0] bin,
    input [15:0] bcd_adj_in,
    output reg [28:0] shift_reg
);
    always @(posedge clk) begin
        if (rst) begin
            shift_reg <= {16'd0, bin};
        end else if (eval) begin
            shift_reg[28:13] <= bcd_adj_in;
        end else if (sumi) begin
            shift_reg <= shift_reg << 1;
        end
    end
endmodule

basic_circuits(implementacion)/test_peripherals/rtl/cores/test/BintoBcd/fsm.v
module fsm_bintobcd (
    input clk,
    input init,
    input reset,
    input need_adj,
    input c,
    input zz,
    output reg rst,
    output reg eval,
    output reg sumi,
    output reg done
);
    parameter START       = 0;
    parameter ESPERAR     = 1;
    parameter CHECKYSUM   = 2;
    parameter SUMARYSHIFT = 3;
    parameter DONE        = 4;
    reg [2:0] state;
 
    always @(posedge clk) begin
        if (reset) begin
            state <= START;
        end else begin
            case (state)
                START:       state <= init     ? ESPERAR   : START;
                ESPERAR:     state <= need_adj  ? CHECKYSUM : SUMARYSHIFT;
                CHECKYSUM:   state <= SUMARYSHIFT;
                SUMARYSHIFT: state <= c         ? DONE      : ESPERAR;
                DONE:        state <= zz        ? START     : DONE;
                default:     state <= START;
            endcase
        end
    end
 
    always @(*) begin
        rst = 1'b0; eval = 1'b0; sumi = 1'b0; done = 1'b0;
        case (state)
            START:  begin     rst  = 1'b1; eval = 1'b0; sumi = 1'b0; done = 1'b0; end
            ESPERAR:   begin  rst = 1'b0; eval = 1'b0; sumi = 1'b0; done = 1'b0; end
            CHECKYSUM:   begin rst = 1'b0; eval = 1'b1; sumi = 1'b0; done = 1'b0; end
            SUMARYSHIFT: begin sumi = 1'b1; rst = 1'b0; eval = 1'b0; done = 1'b0; end
            DONE:    begin    done = 1'b1; rst = 1'b0; eval = 1'b0; sumi = 1'b0;  end
            default: begin
                rst = 1'b0; eval = 1'b0; sumi = 1'b0; done = 1'b0;
            end
        endcase
    end
 
`ifdef BENCH
    reg [8*11:1] state_name;
    always @(*) begin
        case(state)
            START       : state_name = "START";
            ESPERAR     : state_name = "ESPERAR";
            CHECKYSUM   : state_name = "CHECKYSUM";
            SUMARYSHIFT : state_name = "SUMARYSHIFT";
            DONE        : state_name = "DONE";
            default     : state_name = "START";
        endcase
    end
`endif
 
endmodule

Modulos/BintoBcd/BintoBcd.v
module BinToBcd_Top (
    input clk,
    input reset,
    input init,
    input [12:0] bin,
    output [15:0] bcd,
    output done
);
    wire rst, eval, sumi;
 
    wire need_adj, c, zz;
 
    wire [28:0] shift_reg_val;
    wire [15:0] bcd_adj_val;
    wire [4:0]  i_w;
    wire [4:0]  count_w;
 
    assign bcd = shift_reg_val[28:13];
 
    wire [3:0] u       = shift_reg_val[16:13];
    wire [3:0] d       = shift_reg_val[20:17];
    wire [3:0] C = shift_reg_val[24:21];
    wire [3:0] m       = shift_reg_val[28:25];
 
    
    wire [4:0] res_sub_u, res_sub_d, res_sub_c, res_sub_m;
 
    
    wire uu = ~res_sub_u[4];
    wire dd = ~res_sub_d[4];
    wire cc = ~res_sub_c[4];
    wire mm = ~res_sub_m[4];
 
    assign need_adj = (uu | dd | cc | mm);
 
    
    wire [4:0] res_add_u, res_add_d, res_add_c, res_add_m;
 
   
    wire [3:0] u_next = uu ? res_add_u[3:0] : u;
    wire [3:0] d_next = dd ? res_add_d[3:0] : d;
    wire [3:0] c_next = cc ? res_add_c[3:0] : C;
    wire [3:0] m_next = mm ? res_add_m[3:0] : m;
 
    assign bcd_adj_val = {m_next, c_next, d_next, u_next};
 

 
    fsm_bintobcd ControlUnit (
        .clk(clk), .init(init), .reset(reset),
        .need_adj(need_adj), .c(c), .zz(zz),
        .rst(rst), .eval(eval), .sumi(sumi), .done(done)
    );
 
    Registro_Shift_BCD Reg_Datos (
        .clk(clk), .rst(rst), .sumi(sumi), .eval(eval),
        .bin(bin), .bcd_adj_in(bcd_adj_val),
        .shift_reg(shift_reg_val)
    );
 
    SumadorRestador_C2_5b Sub_U (.sum(1'b0), .restar(1'b1), .Aext({1'b0, u}),       .B(5'd5), .result(res_sub_u));
    SumadorRestador_C2_5b Sub_D (.sum(1'b0), .restar(1'b1), .Aext({1'b0, d}),       .B(5'd5), .result(res_sub_d));
    SumadorRestador_C2_5b Sub_C (.sum(1'b0), .restar(1'b1), .Aext({1'b0, C}), .B(5'd5), .result(res_sub_c));
    SumadorRestador_C2_5b Sub_M (.sum(1'b0), .restar(1'b1), .Aext({1'b0, m}),       .B(5'd5), .result(res_sub_m));
 
    SumadorRestador_C2_5b Add_U (.sum(1'b1), .restar(1'b0), .Aext({1'b0, u}),       .B(5'd3), .result(res_add_u));
    SumadorRestador_C2_5b Add_D (.sum(1'b1), .restar(1'b0), .Aext({1'b0, d}),       .B(5'd3), .result(res_add_d));
    SumadorRestador_C2_5b Add_C (.sum(1'b1), .restar(1'b0), .Aext({1'b0, C}), .B(5'd3), .result(res_add_c));
    SumadorRestador_C2_5b Add_M (.sum(1'b1), .restar(1'b0), .Aext({1'b0, m}),       .B(5'd3), .result(res_add_m));
 
    contador Contador_I (
        .clk(clk), .rst(rst), .en(sumi), .count(i_w)
    );
 
    comparador Comp_I (
        .in(i_w), .COMP(5'd12), .equal(c)
    );
 
    contador Contador_Wait (
        .clk(clk), .rst(rst), .en(done), .count(count_w)
    );
 
    comparador Comp_Wait (
        .in(count_w), .COMP(5'd27), .equal(zz)
    );
 
endmodule

Modulos/BintoBcd/BintoBcd_TB.v
`timescale 1ns / 1ps
`define SIMULATION

module BinToBcd_Top_TB;

    
    reg clk;
    reg reset;
    reg init;
    reg [12:0] bin;
    
    
    wire [15:0] bcd;
    wire done;

   
    BinToBcd_Top uut (
        .clk(clk),
        .reset(reset),
        .init(init),
        .bin(bin),
        .bcd(bcd),
        .done(done)
    );

    
    parameter PERIOD          = 40;
    parameter real DUTY_CYCLE = 0.5;
    parameter OFFSET          = 0;

    
    initial begin
        #OFFSET;
        forever begin
            clk = 1'b0;
            #(PERIOD-(PERIOD*DUTY_CYCLE)) clk = 1'b1;
            #(PERIOD*DUTY_CYCLE);
        end
    end

    
    initial begin
        
        #0 reset = 0; init = 0; bin = 13'd0;
        
        
        @(negedge clk);
        reset = 1;
        @(negedge clk);
        reset = 0;
        
        @(negedge clk);  
        bin = 13'd123;
        init = 1;         
        
        @(negedge clk);   
        init = 0;         
        @(negedge done);  
        #200;             
      
        @(negedge clk);   
        bin = 13'd4095;
        init = 1;
        
        @(negedge clk);
        init = 0;
        
        @(negedge done);
        #200;

    
        @(negedge clk);
        bin = 13'd555;
        init = 1;
        
        @(negedge clk);
        init = 0;
        
        @(negedge done);
        #200;
        
        $finish; 
    end

    initial begin: TEST_CASE
        $dumpfile("BinToBcd_Top_TB.vcd");
        $dumpvars(-1, uut);
        #(200000) $finish; 
    end

endmodule

Modulos/BintoBcd/BinToBcd_Top_TB.vcd
$date
	Tue Jul 14 05:33:44 2026
$end
$version
	Icarus Verilog
$end
$timescale
	1ps
$end
$scope module BinToBcd_Top_TB $end
$scope module uut $end
$var wire 13 ! bin [12:0] $end
$var wire 1 " cc $end
$var wire 1 # clk $end
$var wire 1 $ dd $end
$var wire 1 % init $end
$var wire 1 & mm $end
$var wire 1 ' need_adj $end
$var wire 1 ( reset $end
$var wire 1 ) uu $end
$var wire 1 * zz $end
$var wire 4 + u_next [3:0] $end
$var wire 4 , u [3:0] $end
$var wire 1 - sumi $end
$var wire 29 . shift_reg_val [28:0] $end
$var wire 1 / rst $end
$var wire 5 0 res_sub_u [4:0] $end
$var wire 5 1 res_sub_m [4:0] $end
$var wire 5 2 res_sub_d [4:0] $end
$var wire 5 3 res_sub_c [4:0] $end
$var wire 5 4 res_add_u [4:0] $end
$var wire 5 5 res_add_m [4:0] $end
$var wire 5 6 res_add_d [4:0] $end
$var wire 5 7 res_add_c [4:0] $end
$var wire 4 8 m_next [3:0] $end
$var wire 4 9 m [3:0] $end
$var wire 5 : i_w [4:0] $end
$var wire 1 ; eval $end
$var wire 1 < done $end
$var wire 4 = d_next [3:0] $end
$var wire 4 > d [3:0] $end
$var wire 5 ? count_w [4:0] $end
$var wire 4 @ c_next [3:0] $end
$var wire 1 A c $end
$var wire 16 B bcd_adj_val [15:0] $end
$var wire 16 C bcd [15:0] $end
$var wire 4 D C [3:0] $end
$scope module Add_C $end
$var wire 5 E Aext [4:0] $end
$var wire 5 F B [4:0] $end
$var wire 1 G restar $end
$var wire 1 H sum $end
$var reg 5 I result [4:0] $end
$upscope $end
$scope module Add_D $end
$var wire 5 J Aext [4:0] $end
$var wire 5 K B [4:0] $end
$var wire 1 L restar $end
$var wire 1 M sum $end
$var reg 5 N result [4:0] $end
$upscope $end
$scope module Add_M $end
$var wire 5 O Aext [4:0] $end
$var wire 5 P B [4:0] $end
$var wire 1 Q restar $end
$var wire 1 R sum $end
$var reg 5 S result [4:0] $end
$upscope $end
$scope module Add_U $end
$var wire 5 T Aext [4:0] $end
$var wire 5 U B [4:0] $end
$var wire 1 V restar $end
$var wire 1 W sum $end
$var reg 5 X result [4:0] $end
$upscope $end
$scope module Comp_I $end
$var wire 5 Y COMP [4:0] $end
$var wire 5 Z in [4:0] $end
$var wire 1 A equal $end
$upscope $end
$scope module Comp_Wait $end
$var wire 5 [ COMP [4:0] $end
$var wire 5 \ in [4:0] $end
$var wire 1 * equal $end
$upscope $end
$scope module Contador_I $end
$var wire 1 # clk $end
$var wire 1 / rst $end
$var wire 1 - en $end
$var reg 5 ] count [4:0] $end
$upscope $end
$scope module Contador_Wait $end
$var wire 1 # clk $end
$var wire 1 / rst $end
$var wire 1 < en $end
$var reg 5 ^ count [4:0] $end
$upscope $end
$scope module ControlUnit $end
$var wire 1 A c $end
$var wire 1 # clk $end
$var wire 1 % init $end
$var wire 1 ' need_adj $end
$var wire 1 ( reset $end
$var wire 1 * zz $end
$var parameter 32 _ CHECKYSUM $end
$var parameter 32 ` DONE $end
$var parameter 32 a ESPERAR $end
$var parameter 32 b START $end
$var parameter 32 c SUMARYSHIFT $end
$var reg 1 < done $end
$var reg 1 ; eval $end
$var reg 1 / rst $end
$var reg 3 d state [2:0] $end
$var reg 88 e state_name [88:1] $end
$var reg 1 - sumi $end
$upscope $end
$scope module Reg_Datos $end
$var wire 16 f bcd_adj_in [15:0] $end
$var wire 13 g bin [12:0] $end
$var wire 1 # clk $end
$var wire 1 ; eval $end
$var wire 1 / rst $end
$var wire 1 - sumi $end
$var reg 29 h shift_reg [28:0] $end
$upscope $end
$scope module Sub_C $end
$var wire 5 i Aext [4:0] $end
$var wire 5 j B [4:0] $end
$var wire 1 k restar $end
$var wire 1 l sum $end
$var reg 5 m result [4:0] $end
$upscope $end
$scope module Sub_D $end
$var wire 5 n Aext [4:0] $end
$var wire 5 o B [4:0] $end
$var wire 1 p restar $end
$var wire 1 q sum $end
$var reg 5 r result [4:0] $end
$upscope $end
$scope module Sub_M $end
$var wire 5 s Aext [4:0] $end
$var wire 5 t B [4:0] $end
$var wire 1 u restar $end
$var wire 1 v sum $end
$var reg 5 w result [4:0] $end
$upscope $end
$scope module Sub_U $end
$var wire 5 x Aext [4:0] $end
$var wire 5 y B [4:0] $end
$var wire 1 z restar $end
$var wire 1 { sum $end
$var reg 5 | result [4:0] $end
$upscope $end
$upscope $end
$upscope $end
$enddefinitions $end
$comment Show the parameter values. $end
$dumpall
b11 c
b0 b
b1 a
b100 `
b10 _
$end
#0
$dumpvars
bx |
0{
1z
b101 y
b0xxxx x
bx w
0v
1u
b101 t
b0xxxx s
bx r
0q
1p
b101 o
b0xxxx n
bx m
0l
1k
b101 j
b0xxxx i
bx h
b0 g
bx f
bx e
bx d
bx ^
bx ]
bx \
b11011 [
bx Z
b1100 Y
bx X
1W
0V
b11 U
b0xxxx T
bx S
1R
0Q
b11 P
b0xxxx O
bx N
1M
0L
b11 K
b0xxxx J
bx I
1H
0G
b11 F
b0xxxx E
bx D
bx C
bx B
xA
bx @
bx ?
bx >
bx =
x<
x;
bx :
bx 9
bx 8
bx 7
bx 6
bx 5
bx 4
bx 3
bx 2
bx 1
bx 0
x/
bx .
x-
bx ,
bx +
x*
x)
0(
x'
x&
0%
x$
0#
x"
b0 !
$end
#20000
b101001101010100010000010101001001010100 e
0<
0-
0;
1/
b0 d
1#
#40000
1(
0#
#60000
0'
0&
b0 8
0"
b0 @
0$
b0 =
0)
b0 B
b0 f
b0 +
b11011 1
b11011 w
b11 5
b11 S
b11011 3
b11011 m
b11 7
b11 I
b11011 2
b11011 r
b11 6
b11 N
b11011 0
b11011 |
b11 4
b11 X
b0 s
b0 O
b0 9
b0 i
b0 E
b0 D
b0 n
b0 J
b0 >
b0 x
b0 T
b0 ,
b0 C
0*
b0 ?
b0 \
b0 ^
0A
b0 :
b0 Z
b0 ]
b0 .
b0 h
1#
#80000
0(
0#
#100000
1#
#120000
1%
b1111011 !
b1111011 g
0#
#140000
0/
b1000101010100110101000001000101010100100100000101010010 e
b1111011 .
b1111011 h
b1 d
1#
#160000
0%
0#
#180000
b101001101010101010011010100000101010010010110010101001101001000010010010100011001010100 e
1-
b11 d
1#
#200000
0#
#220000
0-
b1000101010100110101000001000101010100100100000101010010 e
b1 :
b1 Z
b1 ]
b11110110 .
b11110110 h
b1 d
1#
#240000
0#
#260000
b101001101010101010011010100000101010010010110010101001101001000010010010100011001010100 e
1-
b11 d
1#
#280000
0#
#300000
0-
b1000101010100110101000001000101010100100100000101010010 e
b10 :
b10 Z
b10 ]
b111101100 .
b111101100 h
b1 d
1#
#320000
0#
#340000
b101001101010101010011010100000101010010010110010101001101001000010010010100011001010100 e
1-
b11 d
1#
#360000
0#
#380000
0-
b1000101010100110101000001000101010100100100000101010010 e
b11 :
b11 Z
b11 ]
b1111011000 .
b1111011000 h
b1 d
1#
#400000
0#
#420000
b101001101010101010011010100000101010010010110010101001101001000010010010100011001010100 e
1-
b11 d
1#
#440000
0#
#460000
0-
b1000101010100110101000001000101010100100100000101010010 e
b100 :
b100 Z
b100 ]
b11110110000 .
b11110110000 h
b1 d
1#
#480000
0#
#500000
b101001101010101010011010100000101010010010110010101001101001000010010010100011001010100 e
1-
b11 d
1#
#520000
0#
#540000
0-
b1000101010100110101000001000101010100100100000101010010 e
b101 :
b101 Z
b101 ]
b111101100000 .
b111101100000 h
b1 d
1#
#560000
0#
#580000
b101001101010101010011010100000101010010010110010101001101001000010010010100011001010100 e
1-
b11 d
1#
#600000
0#
#620000
0-
b1000101010100110101000001000101010100100100000101010010 e
b110 :
b110 Z
b110 ]
b1111011000000 .
b1111011000000 h
b1 d
1#
#640000
0#
#660000
b101001101010101010011010100000101010010010110010101001101001000010010010100011001010100 e
1-
b11 d
1#
#680000
0#
#700000
b1 B
b1 f
b1 +
b11100 0
b11100 |
b100 4
b100 X
b1 x
b1 T
b1 ,
b1 C
0-
b1000101010100110101000001000101010100100100000101010010 e
b111 :
b111 Z
b111 ]
b11110110000000 .
b11110110000000 h
b1 d
1#
#720000
0#
#740000
b101001101010101010011010100000101010010010110010101001101001000010010010100011001010100 e
1-
b11 d
1#
#760000
0#
#780000
b11 B
b11 f
b11 +
b11110 0
b11110 |
b110 4
b110 X
b11 x
b11 T
b11 ,
b11 C
0-
b1000101010100110101000001000101010100100100000101010010 e
b1000 :
b1000 Z
b1000 ]
b111101100000000 .
b111101100000000 h
b1 d
1#
#800000
0#
#820000
b101001101010101010011010100000101010010010110010101001101001000010010010100011001010100 e
1-
b11 d
1#
#840000
0#
#860000
1'
1)
b1010 B
b1010 f
b1010 +
b10 0
b10 |
b1010 4
b1010 X
b111 x
b111 T
b111 ,
b111 C
0-
b1000101010100110101000001000101010100100100000101010010 e
b1001 :
b1001 Z
b1001 ]
b1111011000000000 .
b1111011000000000 h
b1 d
1#
#880000
0#
#900000
b10000110100100001000101010000110100101101011001010100110101010101001101 e
1;
b10 d
1#
#920000
0#
#940000
b1101 B
b1101 f
b1101 +
b101 0
b101 |
b1101 4
b1101 X
b1010 x
b1010 T
b1010 ,
b1010 C
1-
0;
b101001101010101010011010100000101010010010110010101001101001000010010010100011001010100 e
b10101011000000000 .
b10101011000000000 h
b11 d
1#
#960000
0#
#980000
b1000 +
b11000 B
b11000 f
b1 =
b11100 2
b11100 r
b100 6
b100 N
b0 0
b0 |
b1000 4
b1000 X
b1000101010100110101000001000101010100100100000101010010 e
0-
b1 n
b1 J
b1 >
b101 x
b101 T
b101 ,
b10101 C
b1 d
b101010110000000000 .
b101010110000000000 h
b1010 :
b1010 Z
b1010 ]
1#
#1000000
0#
#1020000
1;
b10000110100100001000101010000110100101101011001010100110101010101001101 e
b10 d
1#
#1040000
0#
#1060000
b11011 B
b11011 f
b1011 +
b11 0
b11 |
b1011 4
b1011 X
b101001101010101010011010100000101010010010110010101001101001000010010010100011001010100 e
1-
0;
b1000 x
b1000 T
b1000 ,
b11000 C
b11 d
b110000110000000000 .
b110000110000000000 h
1#
#1080000
0#
#1100000
0'
0)
b0 +
b110000 B
b110000 f
b11 =
b11110 2
b11110 r
b110 6
b110 N
b11011 0
b11011 |
b11 4
b11 X
b11 n
b11 J
b11 >
b0 x
b0 T
b0 ,
b110000 C
0-
b1000101010100110101000001000101010100100100000101010010 e
b1011 :
b1011 Z
b1011 ]
b1100001100000000000 .
b1100001100000000000 h
b1 d
1#
#1120000
0#
#1140000
b101001101010101010011010100000101010010010110010101001101001000010010010100011001010100 e
1-
b11 d
1#
#1160000
0#
#1180000
1'
1$
b1001 =
b1 2
b1 r
b1001 6
b1001 N
b10010001 B
b10010001 f
b1 +
b11100 0
b11100 |
b100 4
b100 X
b110 n
b110 J
b110 >
b1 x
b1 T
b1 ,
b1100001 C
0-
b1000101010100110101000001000101010100100100000101010010 e
1A
b1100 :
b1100 Z
b1100 ]
b11000011000000000000 .
b11000011000000000000 h
b1 d
1#
#1200000
0#
#1220000
b10000110100100001000101010000110100101101011001010100110101010101001101 e
1;
b10 d
1#
#1240000
0#
#1260000
b11000001 B
b11000001 f
b1100 =
b100 2
b100 r
b1100 6
b1100 N
b1001 n
b1001 J
b1001 >
b10010001 C
1-
0;
b101001101010101010011010100000101010010010110010101001101001000010010010100011001010100 e
b100100011000000000000 .
b100100011000000000000 h
b11 d
1#
#1280000
0#
#1300000
0'
0$
b10 =
b1 @
b11100 3
b11100 m
b100 7
b100 I
b11101 2
b11101 r
b101 6
b101 N
b100100011 B
b100100011 f
b11 +
b11110 0
b11110 |
b110 4
b110 X
b1000100010011110100111001000101 e
1<
0-
b1 i
b1 E
b1 D
b10 n
b10 J
b10 >
b11 x
b11 T
b11 ,
b100100011 C
b100 d
b1001000110000000000000 .
b1001000110000000000000 h
0A
b1101 :
b1101 Z
b1101 ]
1#
#1320000
0#
#1340000
b1 ?
b1 \
b1 ^
1#
#1360000
0#
#1380000
b10 ?
b10 \
b10 ^
1#
#1400000
0#
#1420000
b11 ?
b11 \
b11 ^
1#
#1440000
0#
#1460000
b100 ?
b100 \
b100 ^
1#
#1480000
0#
#1500000
b101 ?
b101 \
b101 ^
1#
#1520000
0#
#1540000
b110 ?
b110 \
b110 ^
1#
#1560000
0#
#1580000
b111 ?
b111 \
b111 ^
1#
#1600000
0#
#1620000
b1000 ?
b1000 \
b1000 ^
1#
#1640000
0#
#1660000
b1001 ?
b1001 \
b1001 ^
1#
#1680000
0#
#1700000
b1010 ?
b1010 \
b1010 ^
1#
#1720000
0#
#1740000
b1011 ?
b1011 \
b1011 ^
1#
#1760000
0#
#1780000
b1100 ?
b1100 \
b1100 ^
1#
#1800000
0#
#1820000
b1101 ?
b1101 \
b1101 ^
1#
#1840000
0#
#1860000
b1110 ?
b1110 \
b1110 ^
1#
#1880000
0#
#1900000
b1111 ?
b1111 \
b1111 ^
1#
#1920000
0#
#1940000
b10000 ?
b10000 \
b10000 ^
1#
#1960000
0#
#1980000
b10001 ?
b10001 \
b10001 ^
1#
#2000000
0#
#2020000
b10010 ?
b10010 \
b10010 ^
1#
#2040000
0#
#2060000
b10011 ?
b10011 \
b10011 ^
1#
#2080000
0#
#2100000
b10100 ?
b10100 \
b10100 ^
1#
#2120000
0#
#2140000
b10101 ?
b10101 \
b10101 ^
1#
#2160000
0#
#2180000
b10110 ?
b10110 \
b10110 ^
1#
#2200000
0#
#2220000
b10111 ?
b10111 \
b10111 ^
1#
#2240000
0#
#2260000
b11000 ?
b11000 \
b11000 ^
1#
#2280000
0#
#2300000
b11001 ?
b11001 \
b11001 ^
1#
#2320000
0#
#2340000
b11010 ?
b11010 \
b11010 ^
1#
#2360000
0#
#2380000
1*
b11011 ?
b11011 \
b11011 ^
1#
#2400000
0#
#2420000
1/
0<
b101001101010100010000010101001001010100 e
b0 d
0*
b11100 ?
b11100 \
b11100 ^
1#
#2440000
0#
#2460000
b0 @
b11011 3
b11011 m
b11 7
b11 I
b0 =
b11011 2
b11011 r
b11 6
b11 N
b0 B
b0 f
b0 +
b11011 0
b11011 |
b11 4
b11 X
b0 i
b0 E
b0 D
b0 n
b0 J
b0 >
b0 x
b0 T
b0 ,
b0 C
b0 ?
b0 \
b0 ^
b0 :
b0 Z
b0 ]
b1111011 .
b1111011 h
1#
#2480000
0#
#2500000
1#
#2520000
0#
#2540000
1#
#2560000
0#
#2580000
1#
#2600000
0#
#2620000
1#
#2640000
1%
b111111111111 !
b111111111111 g
0#
#2660000
b1000101010100110101000001000101010100100100000101010010 e
0/
b1 d
b111111111111 .
b111111111111 h
1#
#2680000
0%
0#
#2700000
1-
b101001101010101010011010100000101010010010110010101001101001000010010010100011001010100 e
b11 d
1#
#2720000
0#
#2740000
b1000101010100110101000001000101010100100100000101010010 e
0-
b1 d
b1111111111110 .
b1111111111110 h
b1 :
b1 Z
b1 ]
1#
#2760000
0#
#2780000
1-
b101001101010101010011010100000101010010010110010101001101001000010010010100011001010100 e
b11 d
1#
#2800000
0#
#2820000
b1 B
b1 f
b1 +
b11100 0
b11100 |
b100 4
b100 X
b1000101010100110101000001000101010100100100000101010010 e
0-
b1 x
b1 T
b1 ,
b1 C
b1 d
b11111111111100 .
b11111111111100 h
b10 :
b10 Z
b10 ]
1#
#2840000
0#
#2860000
1-
b101001101010101010011010100000101010010010110010101001101001000010010010100011001010100 e
b11 d
1#
#2880000
0#
#2900000
b11 B
b11 f
b11 +
b11110 0
b11110 |
b110 4
b110 X
b1000101010100110101000001000101010100100100000101010010 e
0-
b11 x
b11 T
b11 ,
b11 C
b1 d
b111111111111000 .
b111111111111000 h
b11 :
b11 Z
b11 ]
1#
#2920000
0#
#2940000
1-
b101001101010101010011010100000101010010010110010101001101001000010010010100011001010100 e
b11 d
1#
#2960000
0#
#2980000
1'
1)
b1010 B
b1010 f
b1010 +
b10 0
b10 |
b1010 4
b1010 X
b1000101010100110101000001000101010100100100000101010010 e
0-
b111 x
b111 T
b111 ,
b111 C
b1 d
b1111111111110000 .
b1111111111110000 h
b100 :
b100 Z
b100 ]
1#
#3000000
0#
#3020000
1;
b10000110100100001000101010000110100101101011001010100110101010101001101 e
b10 d
1#
#3040000
0#
#3060000
b1101 B
b1101 f
b1101 +
b101 0
b101 |
b1101 4
b1101 X
b101001101010101010011010100000101010010010110010101001101001000010010010100011001010100 e
1-
0;
b1010 x
b1010 T
b1010 ,
b1010 C
b11 d
b10101111111110000 .
b10101111111110000 h
1#
#3080000
0#
#3100000
b1000 +
b11000 B
b11000 f
b1 =
b11100 2
b11100 r
b100 6
b100 N
b0 0
b0 |
b1000 4
b1000 X
b1 n
b1 J
b1 >
b101 x
b101 T
b101 ,
b10101 C
0-
b1000101010100110101000001000101010100100100000101010010 e
b101 :
b101 Z
b101 ]
b101011111111100000 .
b101011111111100000 h
b1 d
1#
#3120000
0#
#3140000
b10000110100100001000101010000110100101101011001010100110101010101001101 e
1;
b10 d
1#
#3160000
0#
#3180000
b11011 B
b11011 f
b1011 +
b11 0
b11 |
b1011 4
b1011 X
b1000 x
b1000 T
b1000 ,
b11000 C
1-
0;
b101001101010101010011010100000101010010010110010101001101001000010010010100011001010100 e
b110001111111100000 .
b110001111111100000 h
b11 d
1#
#3200000
0#
#3220000
0'
0)
b1 +
b110001 B
b110001 f
b11 =
b11110 2
b11110 r
b110 6
b110 N
b11100 0
b11100 |
b100 4
b100 X
b1000101010100110101000001000101010100100100000101010010 e
0-
b11 n
b11 J
b11 >
b1 x
b1 T
b1 ,
b110001 C
b1 d
b1100011111111000000 .
b1100011111111000000 h
b110 :
b110 Z
b110 ]
1#
#3240000
0#
#3260000
1-
b101001101010101010011010100000101010010010110010101001101001000010010010100011001010100 e
b11 d
1#
#3280000
0#
#3300000
1'
1$
b1001 =
b1 2
b1 r
b1001 6
b1001 N
b10010011 B
b10010011 f
b11 +
b11110 0
b11110 |
b110 4
b110 X
b1000101010100110101000001000101010100100100000101010010 e
0-
b110 n
b110 J
b110 >
b11 x
b11 T
b11 ,
b1100011 C
b1 d
b11000111111110000000 .
b11000111111110000000 h
b111 :
b111 Z
b111 ]
1#
#3320000
0#
#3340000
1;
b10000110100100001000101010000110100101101011001010100110101010101001101 e
b10 d
1#
#3360000
0#
#3380000
b11000011 B
b11000011 f
b1100 =
b100 2
b100 r
b1100 6
b1100 N
b101001101010101010011010100000101010010010110010101001101001000010010010100011001010100 e
1-
0;
b1001 n
b1001 J
b1001 >
b10010011 C
b11 d
b100100111111110000000 .
b100100111111110000000 h
1#
#3400000
0#
#3420000
0$
b10 =
1)
b1 @
b11100 3
b11100 m
b100 7
b100 I
b11101 2
b11101 r
b101 6
b101 N
b100101010 B
b100101010 f
b1010 +
b10 0
b10 |
b1010 4
b1010 X
b1 i
b1 E
b1 D
b10 n
b10 J
b10 >
b111 x
b111 T
b111 ,
b100100111 C
0-
b1000101010100110101000001000101010100100100000101010010 e
b1000 :
b1000 Z
b1000 ]
b1001001111111100000000 .
b1001001111111100000000 h
b1 d
1#
#3440000
0#
#3460000
b10000110100100001000101010000110100101101011001010100110101010101001101 e
1;
b10 d
1#
#3480000
0#
#3500000
b100101101 B
b100101101 f
b1101 +
b101 0
b101 |
b1101 4
b1101 X
b1010 x
b1010 T
b1010 ,
b100101010 C
1-
0;
b101001101010101010011010100000101010010010110010101001101001000010010010100011001010100 e
b1001010101111100000000 .
b1001010101111100000000 h
b11 d
1#
#3520000
0#
#3540000
1$
b1000 +
b10 @
b11101 3
b11101 m
b101 7
b101 I
b1010001000 B
b1010001000 f
b1000 =
b0 2
b0 r
b1000 6
b1000 N
b0 0
b0 |
b1000 4
b1000 X
b1000101010100110101000001000101010100100100000101010010 e
0-
b10 i
b10 E
b10 D
b101 n
b101 J
b101 >
b101 x
b101 T
b101 ,
b1001010101 C
b1 d
b10010101011111000000000 .
b10010101011111000000000 h
b1001 :
b1001 Z
b1001 ]
1#
#3560000
0#
#3580000
1;
b10000110100100001000101010000110100101101011001010100110101010101001101 e
b10 d
1#
#3600000
0#
#3620000
b1011 =
b1010111011 B
b1010111011 f
b1011 +
b11 2
b11 r
b1011 6
b1011 N
b11 0
b11 |
b1011 4
b1011 X
b101001101010101010011010100000101010010010110010101001101001000010010010100011001010100 e
1-
0;
b1000 n
b1000 J
b1000 >
b1000 x
b1000 T
b1000 ,
b1010001000 C
b11 d
b10100010001111000000000 .
b10100010001111000000000 h
1#
#3640000
0#
#3660000
1"
0$
b1 =
0)
b1 +
b100000010001 B
b100000010001 f
b1000 @
b0 3
b0 m
b1000 7
b1000 I
b11100 2
b11100 r
b100 6
b100 N
b11100 0
b11100 |
b100 4
b100 X
b101 i
b101 E
b101 D
b1 n
b1 J
b1 >
b1 x
b1 T
b1 ,
b10100010001 C
0-
b1000101010100110101000001000101010100100100000101010010 e
b1010 :
b1010 Z
b1010 ]
b101000100011110000000000 .
b101000100011110000000000 h
b1 d
1#
#3680000
0#
#3700000
b10000110100100001000101010000110100101101011001010100110101010101001101 e
1;
b10 d
1#
#3720000
0#
#3740000
b101100010001 B
b101100010001 f
b1011 @
b11 3
b11 m
b1011 7
b1011 I
b1000 i
b1000 E
b1000 D
b100000010001 C
1-
0;
b101001101010101010011010100000101010010010110010101001101001000010010010100011001010100 e
b1000000100011110000000000 .
b1000000100011110000000000 h
b11 d
1#
#3760000
0#
