Modulos/BintoBcd/AjusteBCD.v
module Ajuste_BCD (
    input [15:0] bcd_in,
    output [15:0] bcd_out,
    output need_adj
);
    wire [3:0] u = bcd_in[3:0];
    wire [3:0] d = bcd_in[7:4];
    wire [3:0] c = bcd_in[11:8];
    wire [3:0] m = bcd_in[15:12];
    wire uu = (u >= 5);
    wire dd = (d >= 5);
    wire cc = (c >= 5);
    wire mm = (m >= 5);
    assign need_adj = (uu | dd | cc | mm);
    wire [3:0] u_next = uu ? (u + 3) : u;
    wire [3:0] d_next = dd ? (d + 3) : d;
    wire [3:0] c_next = cc ? (c + 3) : c;
    wire [3:0] m_next = mm ? (m + 3) : m;
    assign bcd_out = {m_next, c_next, d_next, u_next};
endmodule
module comparador (
    input [4:0] in, input [4:0] COMP, output equal                    
);
    assign equal = (in == COMP);
endmodule
module contador (
    input clk, input rst, input en, output reg [4:0] count    
);
    always @(posedge clk) begin
        if (rst) count <= 0; 
        else if (en) count <= count + 1'b1;  
    end
endmodule

Modulos/Divisor/SumadorRestador17_C2/SumadorRestador17_C2.v
module SumadorRestador_C2 (
    input sum,
    input restar,
    input [16:0] Aext,
    input [16:0] B,
    output reg [16:0] result
);

    always @(*) begin
        if (sum) begin
            result = Aext + B;
        end 
        else if (restar) begin
            
            result = Aext + (~B) + 1; 
        end 
        else begin
            result = Aext; 
        end
    end
endmodule

basic_circuits(implementacion)/test_peripherals/rtl/cores/test/Divisor/RegistroC.v
module RegistroCociente (
    input clk,
    input rst,
    input shft,
    input agg,
    output reg [15:0] C
);
    always @(posedge clk) begin
        if (rst) begin
            C <= 0;
        end else begin
            if (shft) begin
                C <= {C[14:0], 1'b0}; 
            end
            if (agg) begin
                C[0] <= 1;
            end
        end
    end
endmodule

Modulos/Multiplicador/RegistroyShifter.v
module RegistroyShifter (
    input clk,
    input rst,      
    input shft,        /
    input [15:0] in, 
    output reg [31:0] in_reg
);
    always @(posedge clk) begin
        if (rst)
            in_reg <= in;
        else if (shft)
            in_reg <= {in_reg[30:0], 1'b0}; 
    end
endmodule

Modulos/Divisor/RegistroAext.v
module RegistroAext (
    input clk,
    input rst,
    input shft,
    input upd_Aext,        
    input [15:0] in_A,     
    input [16:0] alu_in,   
    output reg [16:0] Aext,
    output reg [15:0] A
);
    always @(posedge clk) begin
        if (rst) begin
            Aext <= 17'd0;
            A    <= in_A;
        end 
        else if (shft) begin
            {Aext, A} <= {Aext[15:0], A, 1'b0};
        end 
        else if (upd_Aext) begin
            
            Aext <= alu_in;
        end
    end
endmodule

Modulos/Divisor/control_unit/control_unit.v
module fsm_divisor (
    input clk,
    input init,
    input reset,
    input Aext_16,       
    input c,             
    input zz,            
    output reg rst,
    output reg shft,
    output reg sum,
    output reg restar,
    output reg agg,
    output reg sumi,
    output reg done
);
    reg [2:0] state, next_state;
    
    localparam START    = 3'b000,
               SHIFT    = 3'b001,
               SUMAR    = 3'b010,
               RESTAR   = 3'b011,
               AGREGARC = 3'b100,
               SUMAR_I  = 3'b101,
               SUMAR2   = 3'b110,
               DONE     = 3'b111;

    always @(*) begin
        next_state = state;
        case (state)
            START:    next_state = (init) ? SHIFT : START;
            SHIFT:    next_state = (Aext_16) ? SUMAR : RESTAR;
            SUMAR:    next_state = (Aext_16) ? SUMAR_I : AGREGARC;
            RESTAR:   next_state = (Aext_16) ? SUMAR_I : AGREGARC;
            AGREGARC: next_state = SUMAR_I;
            SUMAR_I:  if (~c) 
                          next_state = SHIFT;
                      else 
                          next_state = (Aext_16) ? SUMAR2 : DONE;
            SUMAR2:   next_state = DONE;
            DONE:     next_state = (zz) ? START : DONE;
            default:  next_state = START;
        endcase
    end

    // CORREGIDO: Ahora corre en posedge clk igual que los registros
    always @(posedge clk) begin
        if (reset) begin
            state <= START;
        end else begin
            state <= next_state;
        end
    end
    
    always @(*) begin
        rst = 0; shft = 0; sum = 0; restar = 0; agg = 0; sumi = 0; done = 0;
        case (state)
            START:    rst = 1;
            SHIFT:    shft = 1;
            SUMAR:    sum = 1;
            RESTAR:   restar = 1;
            AGREGARC: agg = 1;
            SUMAR_I:  sumi = 1;
            SUMAR2:   sum = 1;
            DONE:     done = 1;
        endcase
    end
endmodule

Modulos/Divisor/Divisor.v
module Divisor_Top (
    input clk,
    input reset,
    input init,
    input [15:0] A,
    input [15:0] B,
    output [15:0] Cociente,
    output done
);
    wire rst, shft, sum, restar, agg, sumi;
    wire c, zz;

    wire [16:0] Aextreg;
    wire [15:0] Areg;
    wire [16:0] Breg; 
    wire [16:0] Aext;
    wire [4:0] i_w;
    wire [4:0] count_w; 

    // LÓGICA LOOK-AHEAD: Si estamos en SHIFT, anticipa el signo mirando el bit 15.
    // De lo contrario, lee el signo combinacional de la ALU de forma directa.
    wire Aext_16 = (shft) ? Aextreg[15] : Aext[16]; 
    
    wire upd_Aext = sum | restar;

    fsm_divisor ControlUnit (
        .clk(clk), .init(init), .Aext_16(Aext_16), .c(c), .zz(zz), .reset(reset),
        .rst(rst), .shft(shft), .sum(sum), .restar(restar), .agg(agg), .sumi(sumi), .done(done)
    );

    RegistroAext Reg_Aext_A (
        .clk(clk), .rst(rst), .shft(shft), .upd_Aext(upd_Aext),
        .in_A(A), .alu_in(Aext), .Aext(Aextreg), .A(Areg)
    );
   
    RegistroyShifter Reg_B (
        .clk(clk), .rst(rst), .shft(1'b0), .in(B), .in_reg(Breg)
    );

    RegistroCociente Reg_C (
        .clk(clk), .rst(rst), .shft(shft), .agg(agg), .C(Cociente)
    );

    SumadorRestador_C2 ALU (
        .Aext(Aextreg), .B(Breg), .sum(sum), .restar(restar), .result(Aext)
    );

    contador Contador_I (
        .clk(clk), .rst(rst), .en(sumi), .count(i_w)
    );

    comparador Comp_I (
        .in(i_w), .COMP(5'd16), .equal(c)
    );

    contador Contador_Wait (
        .clk(clk), .rst(rst), .en(done), .count(count_w)
    );

    comparador Comp_Wait (
        .in(count_w), .COMP(5'd28), .equal(zz)
    );

endmodule

Modulos/Divisor/Divisor_TB.v
`timescale 1ns / 1ps
`define SIMULATION

module Divisor_Top_TB;

    reg clk;
    reg reset;
    reg init;
    reg [15:0] A;
    reg [15:0] B;
    
    wire [15:0] Cociente;
    wire done;

    // Instanciación del módulo TOP del divisor
    Divisor_Top uut (
        .clk(clk),
        .reset(reset),
        .init(init),
        .A(A),
        .B(B),
        .Cociente(Cociente),
        .done(done)
    );

    // Parámetros del Reloj
    parameter PERIOD          = 40;
    parameter real DUTY_CYCLE = 0.5;
    parameter OFFSET          = 0;

    initial begin
        #OFFSET;
        forever begin
            clk = 1'b0;
            #(PERIOD-(PERIOD*DUTY_CYCLE)) clk = 1'b1;
            #(PERIOD*DUTY_CYCLE);
        end
    end

    initial begin
        // Inicialización
        #0 reset = 0; init = 0; A = 16'd0; B = 16'd0;
        
        // Reset global del sistema
        @(posedge clk);
        reset = 1;
        @(posedge clk);
        reset = 0;
        
        // Configurar la operación: 100 / 5
        @(posedge clk);
        A = 16'd100;
        B = 16'd5;
        init = 1;               // Pulso de inicio de la máquina de estados
        
        @(posedge clk);
        init = 0;               // Apagar init para evitar bucles de reinicio
        
        // Esperar la bandera de finalización de cómputo de la división
        @(posedge done);
        
        // Dar un margen de tiempo para observar el ciclo de espera final (zz) en GTKWave
        #2000;
        
        $display("Simulacion del Divisor completada.");
        $display("Operacion: %d / %d = %d", A, B, Cociente);
    end

    initial begin: TEST_CASE
        $dumpfile("Divisor_TB.vcd");
        $dumpvars(-1, uut);
        #(100000) $finish; // Fin seguro de simulación
    end

endmodule

Modulos/Divisor/Divisor_TB.vcd
$date
	Thu Jul  9 05:56:47 2026
$end
$version
	Icarus Verilog
$end
$timescale
	1ps
$end
$scope module Divisor_Top_TB $end
$scope module uut $end
$var wire 16 ! A [15:0] $end
$var wire 16 " B [15:0] $end
$var wire 1 # clk $end
$var wire 1 $ init $end
$var wire 1 % reset $end
$var wire 1 & upd_Aext $end
$var wire 1 ' zz $end
$var wire 1 ( sumi $end
$var wire 1 ) sum $end
$var wire 1 * shft $end
$var wire 1 + rst $end
$var wire 1 , restar $end
$var wire 5 - i_w [4:0] $end
$var wire 1 . done $end
$var wire 5 / count_w [4:0] $end
$var wire 1 0 c $end
$var wire 1 1 agg $end
$var wire 16 2 Cociente [15:0] $end
$var wire 17 3 Breg [16:0] $end
$var wire 16 4 Areg [15:0] $end
$var wire 17 5 Aextreg [16:0] $end
$var wire 1 6 Aext_16 $end
$var wire 17 7 Aext [16:0] $end
$scope module ALU $end
$var wire 17 8 B [16:0] $end
$var wire 1 ) sum $end
$var wire 1 , restar $end
$var wire 17 9 Aext [16:0] $end
$var reg 17 : result [16:0] $end
$upscope $end
$scope module Comp_I $end
$var wire 5 ; COMP [4:0] $end
$var wire 5 < in [4:0] $end
$var wire 1 0 equal $end
$upscope $end
$scope module Comp_Wait $end
$var wire 5 = COMP [4:0] $end
$var wire 5 > in [4:0] $end
$var wire 1 ' equal $end
$upscope $end
$scope module Contador_I $end
$var wire 1 # clk $end
$var wire 1 + rst $end
$var wire 1 ( en $end
$var reg 5 ? count [4:0] $end
$upscope $end
$scope module Contador_Wait $end
$var wire 1 # clk $end
$var wire 1 + rst $end
$var wire 1 . en $end
$var reg 5 @ count [4:0] $end
$upscope $end
$scope module ControlUnit $end
$var wire 1 6 Aext_16 $end
$var wire 1 0 c $end
$var wire 1 # clk $end
$var wire 1 $ init $end
$var wire 1 % reset $end
$var wire 1 ' zz $end
$var parameter 3 A AGREGARC $end
$var parameter 3 B DONE $end
$var parameter 3 C RESTAR $end
$var parameter 3 D SHIFT $end
$var parameter 3 E START $end
$var parameter 3 F SUMAR $end
$var parameter 3 G SUMAR2 $end
$var parameter 3 H SUMAR_I $end
$var reg 1 1 agg $end
$var reg 1 . done $end
$var reg 3 I next_state [2:0] $end
$var reg 1 , restar $end
$var reg 1 + rst $end
$var reg 1 * shft $end
$var reg 3 J state [2:0] $end
$var reg 1 ) sum $end
$var reg 1 ( sumi $end
$upscope $end
$scope module Reg_Aext_A $end
$var wire 17 K alu_in [16:0] $end
$var wire 1 # clk $end
$var wire 16 L in_A [15:0] $end
$var wire 1 + rst $end
$var wire 1 * shft $end
$var wire 1 & upd_Aext $end
$var reg 16 M A [15:0] $end
$var reg 17 N Aext [16:0] $end
$upscope $end
$scope module Reg_B $end
$var wire 1 # clk $end
$var wire 16 O in [15:0] $end
$var wire 1 + rst $end
$var wire 1 P shft $end
$var reg 32 Q in_reg [31:0] $end
$upscope $end
$scope module Reg_C $end
$var wire 1 1 agg $end
$var wire 1 # clk $end
$var wire 1 + rst $end
$var wire 1 * shft $end
$var reg 16 R C [15:0] $end
$upscope $end
$upscope $end
$upscope $end
$enddefinitions $end
$comment Show the parameter values. $end
$dumpall
b101 H
b110 G
b10 F
b0 E
b1 D
b11 C
b111 B
b100 A
$end
#0
$dumpvars
bx R
bx Q
0P
b0 O
bx N
bx M
b0 L
bx K
bx J
b0 I
bx @
bx ?
bx >
b11011 =
bx <
b1111 ;
bx :
bx 9
bx 8
bx 7
x6
bx 5
bx 4
bx 3
bx 2
x1
x0
bx /
x.
bx -
x,
x+
x*
x)
x(
x'
x&
0%
0$
0#
b0 "
b0 !
$end
#20000
0&
0.
0(
01
0,
0)
0*
1+
b0 J
1%
1#
#40000
0#
#60000
06
b0 3
b0 8
b0 7
b0 :
b0 K
0'
b0 /
b0 >
b0 @
00
b0 -
b0 <
b0 ?
b0 2
b0 R
b0 Q
b0 4
b0 M
b0 5
b0 9
b0 N
0%
1#
#80000
0#
#100000
b101 3
b101 8
b1100100 4
b1100100 M
b101 Q
b1 I
1$
b101 "
b101 O
b1100100 !
b1100100 L
1#
#120000
0#
#140000
1*
0+
b1 J
b11 I
0$
1#
#160000
0#
#180000
16
1&
b11111111111111011 7
b11111111111111011 :
b11111111111111011 K
1,
0*
b101 I
b11 J
b11001000 4
b11001000 M
1#
#200000
0#
#220000
0&
1(
0,
b1 I
b11111111111111011 5
b11111111111111011 9
b11111111111111011 N
b101 J
1#
#240000
0#
#260000
1*
0(
b10 I
b1 J
b1 -
b1 <
b1 ?
1#
#280000
0#
#300000
1&
1)
0*
b101 I
b11111111111110110 5
b11111111111110110 9
b11111111111110110 N
b110010000 4
b110010000 M
b10 J
1#
#320000
0#
#340000
0&
16
1(
0)
b1 I
b11111111111111011 7
b11111111111111011 :
b11111111111111011 K
b101 J
b11111111111111011 5
b11111111111111011 9
b11111111111111011 N
1#
#360000
0#
#380000
1*
0(
b10 I
b10 -
b10 <
b10 ?
b1 J
1#
#400000
0#
#420000
1&
1)
0*
b101 I
b11111111111111011 7
b11111111111111011 :
b11111111111111011 K
b10 J
b11111111111110110 5
b11111111111110110 9
b11111111111110110 N
b1100100000 4
b1100100000 M
1#
#440000
0#
#460000
0&
1(
0)
b1 I
b11111111111111011 5
b11111111111111011 9
b11111111111111011 N
b101 J
1#
#480000
0#
#500000
1*
0(
b10 I
b1 J
b11 -
b11 <
b11 ?
1#
#520000
0#
#540000
1&
1)
0*
b101 I
b11111111111110110 5
b11111111111110110 9
b11111111111110110 N
b11001000000 4
b11001000000 M
b10 J
1#
#560000
0#
#580000
0&
16
1(
0)
b1 I
b11111111111111011 7
b11111111111111011 :
b11111111111111011 K
b101 J
b11111111111111011 5
b11111111111111011 9
b11111111111111011 N
1#
#600000
0#
#620000
1*
0(
b10 I
b100 -
b100 <
b100 ?
b1 J
1#
#640000
0#
#660000
1&
1)
0*
b101 I
b11111111111111011 7
b11111111111111011 :
b11111111111111011 K
b10 J
b11111111111110110 5
b11111111111110110 9
b11111111111110110 N
b110010000000 4
b110010000000 M
1#
#680000
0#
#700000
0&
1(
0)
b1 I
b11111111111111011 5
b11111111111111011 9
b11111111111111011 N
b101 J
1#
#720000
0#
#740000
1*
0(
b10 I
b1 J
b101 -
b101 <
b101 ?
1#
#760000
0#
#780000
1&
1)
0*
b101 I
b11111111111110110 5
b11111111111110110 9
b11111111111110110 N
b1100100000000 4
b1100100000000 M
b10 J
1#
#800000
0#
#820000
0&
16
1(
0)
b1 I
b11111111111111011 7
b11111111111111011 :
b11111111111111011 K
b101 J
b11111111111111011 5
b11111111111111011 9
b11111111111111011 N
1#
#840000
0#
#860000
1*
0(
b10 I
b110 -
b110 <
b110 ?
b1 J
1#
#880000
0#
#900000
1&
1)
0*
b101 I
b11111111111111011 7
b11111111111111011 :
b11111111111111011 K
b10 J
b11111111111110110 5
b11111111111110110 9
b11111111111110110 N
b11001000000000 4
b11001000000000 M
1#
#920000
0#
#940000
0&
1(
0)
b1 I
b11111111111111011 5
b11111111111111011 9
b11111111111111011 N
b101 J
1#
#960000
0#
#980000
1*
0(
b10 I
b1 J
b111 -
b111 <
b111 ?
1#
#1000000
0#
#1020000
1&
1)
0*
b101 I
b11111111111110110 5
b11111111111110110 9
b11111111111110110 N
b110010000000000 4
b110010000000000 M
b10 J
1#
#1040000
0#
#1060000
0&
16
1(
0)
b1 I
b11111111111111011 7
b11111111111111011 :
b11111111111111011 K
b101 J
b11111111111111011 5
b11111111111111011 9
b11111111111111011 N
1#
#1080000
0#
#1100000
1*
0(
b10 I
b1000 -
b1000 <
b1000 ?
b1 J
1#
#1120000
0#
#1140000
1&
1)
0*
b101 I
b11111111111111011 7
b11111111111111011 :
b11111111111111011 K
b10 J
b11111111111110110 5
b11111111111110110 9
b11111111111110110 N
b1100100000000000 4
b1100100000000000 M
1#
#1160000
0#
#1180000
0&
1(
0)
b1 I
b11111111111111011 5
b11111111111111011 9
b11111111111111011 N
b101 J
1#
#1200000
0#
#1220000
1*
0(
b10 I
b1 J
b1001 -
b1001 <
b1001 ?
1#
#1240000
0#
#1260000
1&
b11111111111111100 7
b11111111111111100 :
b11111111111111100 K
1)
0*
b101 I
b11111111111110111 5
b11111111111110111 9
b11111111111110111 N
b1001000000000000 4
b1001000000000000 M
b10 J
1#
#1280000
0#
#1300000
0&
16
1(
0)
b1 I
b11111111111111100 7
b11111111111111100 :
b11111111111111100 K
b101 J
b11111111111111100 5
b11111111111111100 9
b11111111111111100 N
1#
#1320000
0#
#1340000
1*
0(
b10 I
b1010 -
b1010 <
b1010 ?
b1 J
1#
#1360000
0#
#1380000
1&
1)
0*
b101 I
b11111111111111110 7
b11111111111111110 :
b11111111111111110 K
b10 J
b11111111111111001 5
b11111111111111001 9
b11111111111111001 N
b10000000000000 4
b10000000000000 M
1#
#1400000
0#
#1420000
0&
1(
0)
b1 I
b11111111111111110 5
b11111111111111110 9
b11111111111111110 N
b101 J
1#
#1440000
0#
#1460000
1*
0(
b10 I
b1 J
b1011 -
b1011 <
b1011 ?
1#
#1480000
0#
#1500000
06
1&
b1 7
b1 :
b1 K
1)
0*
b100 I
b11111111111111100 5
b11111111111111100 9
b11111111111111100 N
b100000000000000 4
b100000000000000 M
b10 J
1#
#1520000
0#
#1540000
0&
11
0)
b101 I
b1 7
b1 :
b1 K
b100 J
b1 5
b1 9
b1 N
1#
#1560000
0#
#1580000
1(
01
b1 I
b1 2
b1 R
b101 J
1#
#1600000
0#
#1620000
1*
0(
b11 I
b1 J
b1100 -
b1100 <
b1100 ?
1#
#1640000
0#
#1660000
16
1&
b11111111111111101 7
b11111111111111101 :
b11111111111111101 K
1,
0*
b101 I
b10 2
b10 R
b10 5
b10 9
b10 N
b1000000000000000 4
b1000000000000000 M
b11 J
1#
#1680000
0#
#1700000
0&
1(
0,
b1 I
b11111111111111101 7
b11111111111111101 :
b11111111111111101 K
b101 J
b11111111111111101 5
b11111111111111101 9
b11111111111111101 N
1#
#1720000
0#
#1740000
1*
0(
b10 I
b1101 -
b1101 <
b1101 ?
b1 J
1#
#1760000
0#
#1780000
06
1&
1)
0*
b100 I
b0 7
b0 :
b0 K
b10 J
b11111111111111011 5
b11111111111111011 9
b11111111111111011 N
b0 4
b0 M
b100 2
b100 R
1#
#1800000
0#
#1820000
0&
11
0)
b101 I
b0 5
b0 9
b0 N
b100 J
1#
#1840000
0#
#1860000
1(
01
b1 I
b101 J
b101 2
b101 R
1#
#1880000
0#
#1900000
1*
0(
b11 I
b1110 -
b1110 <
b1110 ?
b1 J
1#
#1920000
0#
#1940000
16
1&
b11111111111111011 7
b11111111111111011 :
b11111111111111011 K
1,
0*
b101 I
b11 J
b1010 2
b1010 R
1#
#1960000
0#
#1980000
0&
1(
0,
b1 I
b11111111111111011 5
b11111111111111011 9
b11111111111111011 N
b101 J
1#
#2000000
0#
#2020000
1*
0(
b10 I
b1 J
10
b1111 -
b1111 <
b1111 ?
1#
#2040000
0#
#2060000
1&
1)
0*
b101 I
b10100 2
b10100 R
b11111111111110110 5
b11111111111110110 9
b11111111111110110 N
b10 J
1#
#2080000
0#
#2100000
0&
16
1(
0)
b110 I
b11111111111111011 7
b11111111111111011 :
b11111111111111011 K
b101 J
b11111111111111011 5
b11111111111111011 9
b11111111111111011 N
1#
#2120000
0#
#2140000
06
1&
b0 7
b0 :
b0 K
1)
0(
b111 I
00
b10000 -
b10000 <
b10000 ?
b110 J
1#
#2160000
0#
#2180000
0&
1.
0)
b0 7
b0 :
b0 K
b111 J
b0 5
b0 9
b0 N
1#
#2200000
0#
#2220000
b1 /
b1 >
b1 @
1#
#2240000
0#
#2260000
b10 /
b10 >
b10 @
1#
#2280000
0#
#2300000
b11 /
b11 >
b11 @
1#
#2320000
0#
#2340000
b100 /
b100 >
b100 @
1#
#2360000
0#
#2380000
b101 /
b101 >
b101 @
1#
#2400000
0#
#2420000
b110 /
b110 >
b110 @
1#
#2440000
0#
#2460000
b111 /
b111 >
b111 @
1#
#2480000
0#
#2500000
b1000 /
b1000 >
b1000 @
1#
#2520000
0#
#2540000
b1001 /
b1001 >
b1001 @
1#
#2560000
0#
#2580000
b1010 /
b1010 >
b1010 @
1#
#2600000
0#
#2620000
b1011 /
b1011 >
b1011 @
1#
#2640000
0#
#2660000
b1100 /
b1100 >
b1100 @
1#
#2680000
0#
#2700000
b1101 /
b1101 >
b1101 @
1#
#2720000
0#
#2740000
b1110 /
b1110 >
b1110 @
1#
#2760000
0#
#2780000
b1111 /
b1111 >
b1111 @
1#
#2800000
0#
#2820000
b10000 /
b10000 >
b10000 @
1#
#2840000
0#
#2860000
b10001 /
b10001 >
b10001 @
1#
#2880000
0#
#2900000
b10010 /
b10010 >
b10010 @
1#
#2920000
0#
#2940000
b10011 /
b10011 >
b10011 @
1#
#2960000
0#
#2980000
b10100 /
b10100 >
b10100 @
1#
#3000000
0#
#3020000
b10101 /
b10101 >
b10101 @
1#
#3040000
0#
#3060000
b10110 /
b10110 >
b10110 @
1#
#3080000
0#
#3100000
b10111 /
b10111 >
b10111 @
1#
#3120000
0#
#3140000
b11000 /
b11000 >
b11000 @
1#
#3160000
0#
#3180000
b11001 /
b11001 >
b11001 @
1#
#3200000
0#
#3220000
b11010 /
b11010 >
b11010 @
1#
#3240000
0#
#3260000
b0 I
1'
b11011 /
b11011 >
b11011 @
1#
#3280000
0#
#3300000
1+
0.
b0 J
0'
b11100 /
b11100 >
b11100 @
1#
#3320000
0#
#3340000
b0 /
b0 >
b0 @
b0 -
b0 <
b0 ?
b0 2
b0 R
b1100100 4
b1100100 M
1#
